factpulse/__init__.py
factpulse/api_client.py
factpulse/api_response.py
factpulse/configuration.py
factpulse/exceptions.py
factpulse/py.typed
factpulse/rest.py
factpulse/api/__init__.py
factpulse/api/afnorpdppa_api.py
factpulse/api/afnorpdppa_directory_service_api.py
factpulse/api/afnorpdppa_flow_service_api.py
factpulse/api/async_tasks_api.py
factpulse/api/chorus_pro_api.py
factpulse/api/client_management_api.py
factpulse/api/downloads_api.py
factpulse/api/electronic_signature_api.py
factpulse/api/factur_x_conversion_api.py
factpulse/api/factur_x_generation_api.py
factpulse/api/factur_x_validation_api.py
factpulse/api/factur_xpdfxml_verification_api.py
factpulse/api/flux10_e_reporting_api.py
factpulse/api/flux6_invoice_lifecycle_cdar_api.py
factpulse/api/health_api.py
factpulse/models/__init__.py
factpulse/models/acknowledgment_status.py
factpulse/models/action_code_info.py
factpulse/models/action_codes_response.py
factpulse/models/additional_document.py
factpulse/models/afnor_acknowledgement.py
factpulse/models/afnor_acknowledgement_detail.py
factpulse/models/afnor_address_edit.py
factpulse/models/afnor_address_patch.py
factpulse/models/afnor_address_put.py
factpulse/models/afnor_address_read.py
factpulse/models/afnor_algorithm.py
factpulse/models/afnor_contains_operator.py
factpulse/models/afnor_create_directory_line_body.py
factpulse/models/afnor_create_directory_line_body_addressing_information.py
factpulse/models/afnor_create_directory_line_body_period.py
factpulse/models/afnor_create_routing_code_body.py
factpulse/models/afnor_credentials.py
factpulse/models/afnor_destination.py
factpulse/models/afnor_diffusion_status.py
factpulse/models/afnor_directory_line_field.py
factpulse/models/afnor_directory_line_payload_history_legal_unit_facility_routing_code.py
factpulse/models/afnor_directory_line_payload_history_legal_unit_facility_routing_code_platform.py
factpulse/models/afnor_directory_line_payload_history_legal_unit_facility_routing_code_routing_code.py
factpulse-4.0.2.dist-info/licenses/LICENSE
factpulse-4.0.2.dist-info/METADATA
factpulse-4.0.2.dist-info/WHEEL
factpulse-4.0.2.dist-info/top_level.txt
factpulse-4.0.2.dist-info/RECORD
