Metadata-Version: 2.4
Name: factpulse
Version: 4.0.2
Summary: FactPulse REST API
Home-page: https://github.com/factpulse/sdk-python
Author: FactPulse
Author-email: FactPulse <contact@factpulse.fr>
License: Proprietary
Project-URL: Repository, https://github.com/GIT_USER_ID/GIT_REPO_ID
Keywords: OpenAPI,OpenAPI-Generator,FactPulse REST API
Requires-Python: >=3.9
License-File: LICENSE
Requires-Dist: urllib3<3.0.0,>=2.1.0
Requires-Dist: python-dateutil>=2.8.2
Requires-Dist: pydantic>=2
Requires-Dist: typing-extensions>=4.7.1
Dynamic: author
Dynamic: home-page
Dynamic: license-file
